Metadata-Version: 2.1
Name: ambivert
Version: 0.5.2
Summary: AmBiVErT - AMplicon BInning Variant caller with ERror Truncation.                 For calling variants in amplicon based sequencing experiments
Home-page: https://git@bitbucket.org/genomematt/ambivert.git
Author: Matthew Wakefield
Author-email: matthew.wakefield@unimelb.edu.au
License: GPLv3
Platform: UNKNOWN
Classifier: Development Status :: 5 - Production/Stable
Classifier: License :: OSI Approved :: GNU General Public License v3 or later (GPLv3+)
Classifier: Operating System :: POSIX
Classifier: Programming Language :: Python :: 3.3
Classifier: Programming Language :: Python :: 3.4
Classifier: Programming Language :: Python :: 3.5
Classifier: Programming Language :: Python :: 3.6
Classifier: Programming Language :: Python :: 3.7
Classifier: Programming Language :: Python :: 3.8
Classifier: Programming Language :: Python :: 3.9
Classifier: Programming Language :: Python :: 3.10
Classifier: Topic :: Scientific/Engineering :: Bio-Informatics
License-File: LICENSE
Requires-Dist: setuptools (>=1.1.6)
